TeXiPy/__init__.py
texipy-0.1.1.dist-info/WHEEL
texipy-0.1.1.dist-info/METADATA
texipy-0.1.1.dist-info/RECORD
