Metadata-Version: 2.1
Name: texipy
Version: 0.1.1
Summary: Python for LaTeX
License: BSD
Author: Praveen Kulkarni
Author-email: praveenneuron@gmail.com
Requires-Python: >=3.9,<4.0
Classifier: License :: Other/Proprietary License
Classifier: Programming Language :: Python :: 3
Classifier: Programming Language :: Python :: 3.9
Classifier: Programming Language :: Python :: 3.10
